pyssword/__init__.py
pyssword/pyssword.py
pyssword/util.py
pyssword-1.0.0.dist-info/LICENSE
pyssword-1.0.0.dist-info/METADATA
pyssword-1.0.0.dist-info/WHEEL
pyssword-1.0.0.dist-info/entry_points.txt
pyssword-1.0.0.dist-info/top_level.txt
pyssword-1.0.0.dist-info/RECORD
