Metadata-Version: 2.1
Name: pyssword
Version: 1.0.0
Summary: A Python password generator.
Author-email: Vitor Assis <vitor.assis.dev@gmail.com>
Maintainer-email: Vitor Assis <vitor.assis.dev@gmail.com>
License: The MIT License (MIT)
Project-URL: Homepage, https://pypi.org/project/pyssword
Project-URL: Repository, https://gitlab.com/vassis/pyssword
Project-URL: Documentation, https://gitlab.com/vassis/pyssword/-/blob/master/README.md
Keywords: cli,criptography,password,pyssword,python3
Classifier: Development Status :: 2 - Pre-Alpha
Classifier: License :: OSI Approved :: MIT License
Classifier: Programming Language :: Python :: 3
Classifier: Operating System :: POSIX :: Linux
Classifier: Intended Audience :: End Users/Desktop
Classifier: Intended Audience :: Developers
Classifier: Topic :: Security :: Cryptography
Classifier: Environment :: Console
Classifier: Environment :: X11 Applications
Classifier: Natural Language :: Portuguese (Brazilian)
Classifier: Natural Language :: English
Requires-Python: >=3.8
License-File: LICENSE
Requires-Dist: click
Provides-Extra: dev
Requires-Dist: build ; extra == 'dev'
Requires-Dist: pytest >=6.0 ; extra == 'dev'
Requires-Dist: twine ; extra == 'dev'
